finesql/__init__.py
finesql/orm.py
finesql-0.1.3.4.dist-info/licenses/LICENSE
finesql-0.1.3.4.dist-info/METADATA
finesql-0.1.3.4.dist-info/WHEEL
finesql-0.1.3.4.dist-info/top_level.txt
finesql-0.1.3.4.dist-info/RECORD
