Metadata-Version: 2.4
Name: finesql
Version: 0.1.3.4
Summary: FineSQL is a library for interacting with SQLite database from Python code, with Python objects.
Author-email: Abdelmajid Yunus <goldendevuz@gmail.com>
License: MIT
Project-URL: Homepage, https://github.com/goldendevuz/finesql
Project-URL: Documentation, https://goldendevuz.github.io/finesql-docs
Project-URL: Repository, https://github.com/goldendevuz/finesql
Project-URL: Issues, https://github.com/goldendevuz/finesql/issues
Project-URL: Changelog, https://sqlmodel.tiangolo.com/release-notes
Keywords: web,framework,object,sqlite,orm
Classifier: Development Status :: 3 - Alpha
Classifier: Framework :: AsyncIO
Classifier: Intended Audience :: Developers
Classifier: License :: OSI Approved :: MIT License
Classifier: Programming Language :: Python :: 3 :: Only
Classifier: Programming Language :: Python :: 3.8
Classifier: Programming Language :: Python :: 3.9
Classifier: Programming Language :: Python :: 3.10
Classifier: Programming Language :: Python :: 3.11
Classifier: Programming Language :: Python :: 3.12
Classifier: Programming Language :: Python :: 3.13
Classifier: Topic :: Database
Classifier: Topic :: Database :: Database Engines/Servers
Classifier: Topic :: Internet
Classifier: Topic :: Internet :: WWW/HTTP :: HTTP Servers
Classifier: Topic :: Internet :: WWW/HTTP
Classifier: Typing :: Typed
Requires-Python: >=3.9
License-File: LICENSE
Requires-Dist: build==1.3.0
Requires-Dist: icecream==2.1.8
Requires-Dist: pytest==8.4.2
Requires-Dist: setuptools==80.9.0
Requires-Dist: twine==6.2.0
Requires-Dist: wheel==0.45.1
Provides-Extra: dev
Requires-Dist: pytest==8.4.2; extra == "dev"
Requires-Dist: setuptools==80.9.0; extra == "dev"
Requires-Dist: twine==6.2.0; extra == "dev"
Requires-Dist: wheel==0.45.1; extra == "dev"
Requires-Dist: icecream==2.1.8; extra == "dev"
Requires-Dist: setuptools==80.9.0; extra == "dev"
Requires-Dist: build==1.3.0; extra == "dev"
Dynamic: license-file
